eatery_nod/EateryNod.py
eatery_nod/EateryWebsocket.py
eatery_nod/Exceptions.py
eatery_nod/__init__.py
lunchbot_python-0.1.1.dist-info/LICENSE
lunchbot_python-0.1.1.dist-info/METADATA
lunchbot_python-0.1.1.dist-info/WHEEL
lunchbot_python-0.1.1.dist-info/top_level.txt
lunchbot_python-0.1.1.dist-info/RECORD
