Metadata-Version: 2.1
Name: lunchbot-python
Version: 0.1.1
Summary: Python interface for the Lunchbot API.
Home-page: https://github.com/sotpotatis/Lunchbot-Python
Author: Albin Seijmer
Author-email: albinsmejladress@protonmail.com
License: MIT
Platform: UNKNOWN
Classifier: Programming Language :: Python :: 3
Classifier: Programming Language :: Python :: 3.7
Classifier: Development Status :: 3 - Alpha
Classifier: Intended Audience :: Developers
Classifier: License :: OSI Approved :: MIT License
Requires: requests
Requires: websocket
Requires: pytz
